{
  "export_settings": {
    "fileType": "Binary",
    "fbxVersion": "2018",
    "embedMedia": true,
    "bakeAnimation": true,
    "moveToOrigin": false,
    "exportPath": "G:/STALKER2_AnimationSource/Testing",
    "clipPrefix": "",
    "exportMode": "Export Selected Clips",
    "currentPreset": "<None>",
    "rotationOffset": {
      "enabled": true,
      "joint": "Main",
      "rotationX": 0.0,
      "rotationY": 90.0,
      "rotationZ": 0.0
    }
  },
  "root_joints": [
    "jnt_root",
    "jnt_hips",
    "jnt_spine_01",
    "jnt_spine_02",
    "jnt_spine_03",
    "jnt_neck",
    "jnt_head",
    "jnt_r_shoulder",
    "jnt_r_arm",
    "jnt_r_fore_arm",
    "jnt_r_hand",
    "jnt_r_hand_thumb_01",
    "jnt_r_hand_thumb_02",
    "jnt_r_hand_thumb_03",
    "jnt_r_hand_index_meta",
    "jnt_r_hand_index_01",
    "jnt_r_hand_index_02",
    "jnt_r_hand_index_03",
    "jnt_r_hand_middle_meta",
    "jnt_r_hand_middle_01",
    "jnt_r_hand_middle_02",
    "jnt_r_hand_middle_03",
    "jnt_r_hand_ring_meta",
    "jnt_r_hand_ring_01",
    "jnt_r_hand_ring_02",
    "jnt_r_hand_ring_03",
    "jnt_r_hand_pinky_meta",
    "jnt_r_hand_pinky_01",
    "jnt_r_hand_pinky_02",
    "jnt_r_hand_pinky_03",
    "jnt_r_weapon",
    "jnt_r_fore_arm_roll",
    "jnt_r_fore_arm_down",
    "jnt_r_fore_arm_left",
    "jnt_r_fore_arm_up",
    "jnt_r_fore_arm_right",
    "jnt_r_elbow",
    "jnt_r_arm_roll",
    "jnt_r_shoulder_armor",
    "jnt_r_armor",
    "jnt_l_shoulder",
    "jnt_l_arm",
    "jnt_l_fore_arm",
    "jnt_l_hand",
    "jnt_l_hand_thumb_01",
    "jnt_l_hand_thumb_02",
    "jnt_l_hand_thumb_03",
    "jnt_l_hand_index_meta",
    "jnt_l_hand_index_01",
    "jnt_l_hand_index_02",
    "jnt_l_hand_index_03",
    "jnt_l_hand_middle_meta",
    "jnt_l_hand_middle_01",
    "jnt_l_hand_middle_02",
    "jnt_l_hand_middle_03",
    "jnt_l_hand_ring_meta",
    "jnt_l_hand_ring_01",
    "jnt_l_hand_ring_02",
    "jnt_l_hand_ring_03",
    "jnt_l_hand_pinky_meta",
    "jnt_l_hand_pinky_01",
    "jnt_l_hand_pinky_02",
    "jnt_l_hand_pinky_03",
    "jnt_l_weapon",
    "jnt_l_fore_arm_roll",
    "jnt_l_fore_arm_down",
    "jnt_l_fore_arm_left",
    "jnt_l_fore_arm_up",
    "jnt_l_fore_arm_right",
    "jnt_l_elbow",
    "jnt_l_arm_roll",
    "jnt_l_shoulder_armor",
    "jnt_l_armor",
    "jnt_f_spine_bag",
    "jnt_b_spine_bag",
    "jnt_r_up_leg",
    "jnt_r_leg",
    "jnt_r_foot",
    "jnt_r_toe_base",
    "jnt_r_knee",
    "jnt_r_up_leg_roll",
    "jnt_r_leg_bag",
    "jnt_l_up_leg",
    "jnt_l_leg",
    "jnt_l_foot",
    "jnt_l_toe_base",
    "jnt_l_knee",
    "jnt_l_up_leg_roll",
    "jnt_l_leg_bag",
    "jnt_l_hips_bag2",
    "jnt_l_hips_bag",
    "jnt_f_hips_bag",
    "jnt_b_hips_bag",
    "jnt_camera",
    "jnt_weapon",
    "jnt_ik_hand_root",
    "jnt_ik_hand_gun",
    "jnt_r_ik_hand",
    "jnt_l_ik_hand",
    "jnt_ik_foot_root",
    "jnt_r_ik_foot",
    "jnt_l_ik_foot",
    "jnt_root_weapon",
    "jnt_second_weapon",
    "jnt_unequipped_weapon",
    "jnt_item",
    "jnt_unequipped_second",
    "jnt_unequipped_item",
    "jnt_additional",
    "jnt_additional_second"
  ],
  "animation_layer_states": {
    "Base Animation": true,
    "BaseAnimation": true,
    "S2_Rig:BaseAnimation": true
  }
}